ani_sync/__init__.py
ani_sync/config.py
ani_sync/hsts_parser.py
ani_sync/main.py
ani_sync/sync_client.py
ani_sync-0.1.1.dist-info/LICENSE
ani_sync-0.1.1.dist-info/METADATA
ani_sync-0.1.1.dist-info/WHEEL
ani_sync-0.1.1.dist-info/entry_points.txt
ani_sync-0.1.1.dist-info/top_level.txt
ani_sync-0.1.1.dist-info/RECORD
