Metadata-Version: 2.1
Name: ani-sync
Version: 0.1.1
Summary: Sync your ani-cli progress with a remote server.
Home-page: https://github.com/Hamziee/ani-sync
Author: HamzieDev
Author-email: hamza@heo-systems.net
Classifier: Programming Language :: Python :: 3
Classifier: License :: OSI Approved :: GNU General Public License v3 (GPLv3) 
Classifier: Operating System :: OS Independent
Requires-Python: >=3.6
License-File: LICENSE
Requires-Dist: requests
